superdupper/db/__init__.py
superdupper/db/orm.py
superdupper_db-0.0.17.dist-info/METADATA
superdupper_db-0.0.17.dist-info/WHEEL
superdupper_db-0.0.17.dist-info/top_level.txt
superdupper_db-0.0.17.dist-info/RECORD
