Metadata-Version: 2.1
Name: superdupper-db
Version: 0.0.17
Summary: Superdupper db.
